{"symbol": "COP", "fetched_at": "2025-12-02T13:05:34.376634", "current_price": 88.9872, "previous_close": 90.26, "day_change_pct": -1.4101532, "volume": 1930820, "avg_volume": 6661923, "avg_volume_10day": 6350470, "market_cap": 111139880960, "shares_outstanding": 1235718250, "pe_ratio": 12.568813, "pb_ratio": 1.693736, "ps_ratio": 1.8136402, "peg_ratio": 0, "revenue_growth": 0.14, "earnings_growth": -0.216, "earnings_quarterly_growth": -0.162, "profit_margin": 0.14445, "operating_margin": 0.19543, "gross_margin": 0.47415, "roe": 0.15421, "roa": 0.080979995, "debt_to_equity": 36.169, "current_ratio": 1.323, "quick_ratio": 0.999, "free_cash_flow": 6092499968, "operating_cash_flow": 19935000576, "dividend_yield": 3.72, "payout_ratio": 0.4407, "target_price": 112.85714, "recommendation": "buy", "num_analyst_opinions": 28, "52week_high": 107.67, "52week_low": 79.88, "50day_avg": 89.9568, "200day_avg": 92.4914, "sector": "Energy", "industry": "Oil & Gas E&P", "pct_from_52week_high": -17.351908609640567, "volume_ratio": 0.28982922798717425, "price_change_5d": 2.732850443701861, "price_change_20d": 2.1645744371205144, "price_change_60d": -2.228518800699069}